sqlpandas/SQLpandas.py
sqlpandas/__init__.py
sqlpandas-0.1.dist-info/DESCRIPTION.rst
sqlpandas-0.1.dist-info/METADATA
sqlpandas-0.1.dist-info/RECORD
sqlpandas-0.1.dist-info/WHEEL
sqlpandas-0.1.dist-info/metadata.json
sqlpandas-0.1.dist-info/top_level.txt
