Metadata-Version: 2.0
Name: sqlpandas
Version: 0.1
Summary: Native SQL Wrapper for Pandas
Home-page: https://github.com/jvlingam/SQLpandas
Author: Vijay Lingam
Author-email: jvlingam@gmail.com
License: VijayLingam
Platform: All
